dfainductor/__about__.py
dfainductor/__init__.py
dfainductor/examples.py
dfainductor/logging_utils.py
dfainductor/main.py
dfainductor/statistics.py
dfainductor/structures.py
dfainductor/variables.py
dfainductor/algorithms/__init__.py
dfainductor/algorithms/reductions.py
dfainductor/algorithms/searchers.py
dfainductor-0.1.3.dist-info/LICENSE
dfainductor-0.1.3.dist-info/METADATA
dfainductor-0.1.3.dist-info/WHEEL
dfainductor-0.1.3.dist-info/entry_points.txt
dfainductor-0.1.3.dist-info/top_level.txt
dfainductor-0.1.3.dist-info/RECORD
