Metadata-Version: 2.1
Name: dfainductor
Version: 0.1.3
Summary: A python tool for solving minDFA problem.
Home-page: https://github.com/ctlab/DFA-Inductor-py
Author: Ilya Zakirzyanov
Author-email: ilya.zakirzyanov@gmail.com
License: MIT
Platform: UNKNOWN
Classifier: Intended Audience :: Science/Research
Classifier: License :: OSI Approved :: MIT License
Classifier: Natural Language :: English
Classifier: Natural Language :: Russian
Classifier: Programming Language :: Python :: 3.7
Classifier: Programming Language :: Python :: 3.8
Classifier: Topic :: Scientific/Engineering :: Artificial Intelligence
Classifier: Topic :: Scientific/Engineering :: Mathematics
Requires-Python: >=3.7
Requires-Dist: python-sat
Requires-Dist: click
Provides-Extra: dev
Requires-Dist: pytest ; extra == 'dev'
